experiment/cordic_trig_8bit.v
module cordic_trig(
    input wire clk,
    input wire rst,
    input wire [7:0] angle,     // Input angle in range 0-255 (0 to 2π)
    output reg [7:0] sine,      // Scaled sine output
    output reg [7:0] cosine     // Scaled cosine output
);

    // Constants for CORDIC angles (atan values)
    reg [7:0] atan_table [0:7];
    initial begin
        atan_table[0] = 8'd64;  // atan(1)    ≈ 45°
        atan_table[1] = 8'd38;  // atan(1/2)  ≈ 26.57°
        atan_table[2] = 8'd20;  // atan(1/4)  ≈ 14.04°
        atan_table[3] = 8'd10;  // atan(1/8)  ≈ 7.13°
        atan_table[4] = 8'd5;   // atan(1/16) ≈ 3.58°
        atan_table[5] = 8'd3;   // atan(1/32) ≈ 1.79°
        atan_table[6] = 8'd1;   // atan(1/64) ≈ 0.89°
        atan_table[7] = 8'd1;   // atan(1/128)≈ 0.45°
    end

    // Internal registers
    reg [8:0] x, x_next;
    reg [8:0] y, y_next;
    reg [7:0] z, z_next;
    reg [3:0] iteration;
    
    // CORDIC scaling factor compensation (K ≈ 0.607)
    parameter SCALE = 8'd78;    // 0.607 * 128

    always @(posedge clk or posedge rst) begin
        if (rst) begin
            x <= SCALE;         // Initialize with scaling factor
            y <= 9'd0;
            z <= angle;
            iteration <= 4'd0;
        end else if (iteration < 8) begin
            // Determine rotation direction
            if (z[7]) begin     // Negative angle
                x_next = x + (y >>> iteration);
                y_next = y - (x >>> iteration);
                z_next = z + atan_table[iteration];
            end else begin      // Positive angle
                x_next = x - (y >>> iteration);
                y_next = y + (x >>> iteration);
                z_next = z - atan_table[iteration];
            end
            
            x <= x_next;
            y <= y_next;
            z <= z_next;
            iteration <= iteration + 1;
        end
        
        // Output scaled results
        cosine <= x[8:1];      // Scale down and take upper bits
        sine <= y[8:1];        // Scale down and take upper bits
    end
endmodule

experiment/tb_cordic_trig_8bit.v
module cordic_trig_tb;
    // Signal declarations
    reg clk;
    reg rst;
    reg [7:0] angle;
    wire [7:0] sine;
    wire [7:0] cosine;
    
    // Instantiate the DUT
    cordic_trig dut (
        .clk(clk),
        .rst(rst),
        .angle(angle),
        .sine(sine),
        .cosine(cosine)
    );
    
    // Clock generation
    initial begin
        clk = 0;
        forever #5 clk = ~clk;
    end
    
    // Test stimulus
    initial begin
        // Test case 1: Reset
        rst = 1;
        angle = 8'd0;
        #10;
        rst = 0;
        #10;
        
        // Test case 2: 0 degrees
        angle = 8'd0;
        #20;
        if (cosine !== 8'b01111111 || sine !== 8'b00000000)
            $display("Error: 0 degrees test failed");
            
        // Test case 3: 45 degrees
        angle = 8'd64;
        #20;
        if (cosine <= 8'b01011010 || sine <= 8'b01011010)
            $display("Error: 45 degrees test failed");
            
        // Test case 4: 90 degrees
        angle = 8'd128;
        #20;
        if (cosine !== 8'b00000000 || sine !== 8'b01111111)
            $display("Error: 90 degrees test failed");
            
        // Test case 5: 180 degrees
        angle = 8'd255;
        #20;
        if (cosine >= 8'b10000000 || sine !== 8'b00000000)
            $display("Error: 180 degrees test failed");
            
        // Test case 6: Rapid angle changes
        angle = 8'd32;  // 22.5 degrees
        #10;
        angle = 8'd96;  // 67.5 degrees
        #10;
        angle = 8'd160; // 112.5 degrees
        #10;
        
        // End simulation
        #100;
        $display("Test completed");
        $finish;
    end
    
    // Optional waveform dump
    initial begin
        $dumpfile("cordic_test.vcd");
        $dumpvars(0, cordic_trig_tb);
    end
    
endmodule

experiment/cordic_test.vcd
$date
	Mon Nov 25 16:49:28 2024
$end
$version
	Icarus Verilog
$end
$timescale
	1s
$end
$scope module cordic_trig_tb $end
$var wire 8 ! sine [7:0] $end
$var wire 8 " cosine [7:0] $end
$var reg 8 # angle [7:0] $end
$var reg 1 $ clk $end
$var reg 1 % rst $end
$scope module dut $end
$var wire 8 & angle [7:0] $end
$var wire 1 $ clk $end
$var wire 1 % rst $end
$var parameter 8 ' SCALE $end
$var reg 8 ( cosine [7:0] $end
$var reg 4 ) iteration [3:0] $end
$var reg 8 * sine [7:0] $end
$var reg 9 + x [8:0] $end
$var reg 9 , x_next [8:0] $end
$var reg 9 - y [8:0] $end
$var reg 9 . y_next [8:0] $end
$var reg 8 / z [7:0] $end
$var reg 8 0 z_next [7:0] $end
$upscope $end
$upscope $end
$enddefinitions $end
$comment Show the parameter values. $end
$dumpall
b1001110 '
$end
#0
$dumpvars
bx 0
b0 /
bx .
b0 -
bx ,
b1001110 +
bx *
b0 )
bx (
b0 &
1%
0$
b0 #
bx "
bx !
$end
#5
b0 !
b0 *
b100111 "
b100111 (
1$
#10
0$
0%
#15
b1 )
b11000000 /
b1001110 -
b11000000 0
b1001110 .
b1001110 ,
1$
#20
0$
#25
b100111 !
b100111 *
b10 )
b11100110 /
b100111 -
b1110101 +
b11100110 0
b100111 .
b1110101 ,
1$
#30
0$
#35
b10011 !
b10011 *
b111010 "
b111010 (
b11 )
b11111010 /
b1010 -
b1111110 +
b11111010 0
b1010 .
b1111110 ,
1$
#40
0$
b1000000 #
b1000000 &
#45
b101 !
b101 *
b111111 "
b111111 (
b100 )
b100 /
b111111011 -
b1111111 +
b100 0
b111111011 .
b1111111 ,
1$
#50
0$
#55
b11111101 !
b11111101 *
b101 )
b11111111 /
b10 -
b1100000 +
b11111111 0
b10 .
b1100000 ,
1$
#60
0$
b10000000 #
b10000000 &
#65
b1 !
b1 *
b110000 "
b110000 (
b110 )
b10 /
b111111111 -
b10 0
b111111111 .
1$
#70
0$
#75
b11111111 !
b11111111 *
b111 )
b1 /
b0 -
b1011001 +
b1 0
b0 .
b1011001 ,
1$
#80
0$
b11111111 #
b11111111 &
#85
b0 !
b0 *
b101100 "
b101100 (
b1000 )
b0 /
b0 0
1$
#90
0$
#95
1$
#100
0$
b100000 #
b100000 &
#105
1$
#110
0$
b1100000 #
b1100000 &
#115
1$
#120
0$
b10100000 #
b10100000 &
