experiment/cordic_sqrt_8bit.v
module cordic_sqrt(
    input wire clk,
    input wire rst,
    input wire [7:0] value,  // Input value to compute sqrt
    output reg [7:0] sqrt
);

    // Internal registers
    reg [15:0] x, x_next;
    reg [15:0] y, y_next;
    reg [7:0] z, z_next;
    reg [7:0] iteration;

    always @(posedge clk or posedge rst) begin
        if (rst) begin
            x <= 16'd0;
            y <= {8'b0, value};
            z <= 8'd128;  // Start with half of the max value
            iteration <= 8'd0;
        end else if (iteration < 8) begin
            x_next = x + (y >>> iteration);
            y_next = y - (x >>> iteration);
            z_next = z - (1 << (7 - iteration));
            iteration <= iteration + 1;
            x <= x_next;
            y <= y_next;
            z <= z_next;
        end
        sqrt <= x[15:8];
    end
endmodule

experiment/tb_cordic_sqrt_8bit.v
`timescale 1ns/1ps

module cordic_sqrt_tb;
    reg clk;
    reg rst;
    reg [7:0] value;
    wire [7:0] sqrt;
    
    // Instantiate the CORDIC sqrt module
    cordic_sqrt uut (
        .clk(clk),
        .rst(rst),
        .value(value),
        .sqrt(sqrt)
    );
    
    // Clock generation
    initial begin
        clk = 0;
        forever #5 clk = ~clk;
    end
    
    // Test stimulus
    initial begin
        // Initialize waveform dump
        $dumpfile("cordic_sqrt.vcd");
        $dumpvars(0, cordic_sqrt_tb);
        
        // Test case 1: Reset behavior
        rst = 1;
        value = 8'd0;
        #10;
        rst = 0;
        #100;
        
        // Test case 2: Perfect squares
        value = 8'd16;  // sqrt(16) = 4
        #100;
        if (sqrt !== 8'd4) $display("Error: sqrt(16) = %d, expected 4", sqrt);
        
        value = 8'd64;  // sqrt(64) = 8
        #100;
        if (sqrt !== 8'd8) $display("Error: sqrt(64) = %d, expected 8", sqrt);
        
        // Test case 3: Edge cases
        value = 8'd0;   // sqrt(0) = 0
        #100;
        if (sqrt !== 8'd0) $display("Error: sqrt(0) = %d, expected 0", sqrt);
        
        value = 8'd255; // sqrt(255) ≈ 15
        #100;
        if (sqrt !== 8'd15) $display("Error: sqrt(255) = %d, expected 15", sqrt);
        
        // Test case 4: Non-perfect squares
        value = 8'd10;  // sqrt(10) ≈ 3
        #100;
        if (sqrt !== 8'd3) $display("Error: sqrt(10) = %d, expected 3", sqrt);
        
        value = 8'd50;  // sqrt(50) ≈ 7
        #100;
        if (sqrt !== 8'd7) $display("Error: sqrt(50) = %d, expected 7", sqrt);
        
        // Test case 5: Rapid value changes
        value = 8'd100;
        #20;
        value = 8'd81;
        #20;
        value = 8'd36;
        #100;
        
        $display("All tests completed");
        $finish;
    end
    
    // Optional: Monitor changes
    initial begin
        $monitor("Time=%0t rst=%b value=%d sqrt=%d", $time, rst, value, sqrt);
    end
endmodule

experiment/cordic_sqrt.vcd
$date
	Mon Nov 25 16:37:36 2024
$end
$version
	Icarus Verilog
$end
$timescale
	1ps
$end
$scope module cordic_sqrt_tb $end
$var wire 8 ! sqrt [7:0] $end
$var reg 1 " clk $end
$var reg 1 # rst $end
$var reg 8 $ value [7:0] $end
$scope module uut $end
$var wire 1 " clk $end
$var wire 1 # rst $end
$var wire 8 % value [7:0] $end
$var reg 8 & iteration [7:0] $end
$var reg 8 ' sqrt [7:0] $end
$var reg 16 ( x [15:0] $end
$var reg 16 ) x_next [15:0] $end
$var reg 16 * y [15:0] $end
$var reg 16 + y_next [15:0] $end
$var reg 8 , z [7:0] $end
$var reg 8 - z_next [7:0] $end
$upscope $end
$upscope $end
$enddefinitions $end
$comment Show the parameter values. $end
$dumpall
$end
#0
$dumpvars
bx -
b10000000 ,
bx +
b0 *
bx )
b0 (
bx '
b0 &
b0 %
b0 $
1#
0"
bx !
$end
#5000
b0 !
b0 '
1"
#10000
0"
0#
#15000
b0 ,
b1 &
b0 -
b0 +
b0 )
1"
#20000
0"
#25000
b11000000 ,
b10 &
b11000000 -
1"
#30000
0"
#35000
b10100000 ,
b11 &
b10100000 -
1"
#40000
0"
#45000
b10010000 ,
b100 &
b10010000 -
1"
#50000
0"
#55000
b10001000 ,
b101 &
b10001000 -
1"
#60000
0"
#65000
b10000100 ,
b110 &
b10000100 -
1"
#70000
0"
#75000
b10000010 ,
b111 &
b10000010 -
1"
#80000
0"
#85000
b10000001 ,
b1000 &
b10000001 -
1"
#90000
0"
#95000
1"
#100000
0"
#105000
1"
#110000
0"
b10000 $
b10000 %
#115000
1"
#120000
0"
#125000
1"
#130000
0"
#135000
1"
#140000
0"
#145000
1"
#150000
0"
#155000
1"
#160000
0"
#165000
1"
#170000
0"
#175000
1"
#180000
0"
#185000
1"
#190000
0"
#195000
1"
#200000
0"
#205000
1"
#210000
0"
b1000000 $
b1000000 %
#215000
1"
#220000
0"
#225000
1"
#230000
0"
#235000
1"
#240000
0"
#245000
1"
#250000
0"
#255000
1"
#260000
0"
#265000
1"
#270000
0"
#275000
1"
#280000
0"
#285000
1"
#290000
0"
#295000
1"
#300000
0"
#305000
1"
#310000
0"
b0 $
b0 %
#315000
1"
#320000
0"
#325000
1"
#330000
0"
#335000
1"
#340000
0"
#345000
1"
#350000
0"
#355000
1"
#360000
0"
#365000
1"
#370000
0"
#375000
1"
#380000
0"
#385000
1"
#390000
0"
#395000
1"
#400000
0"
#405000
1"
#410000
0"
b11111111 $
b11111111 %
#415000
1"
#420000
0"
#425000
1"
#430000
0"
#435000
1"
#440000
0"
#445000
1"
#450000
0"
#455000
1"
#460000
0"
#465000
1"
#470000
0"
#475000
1"
#480000
0"
#485000
1"
#490000
0"
#495000
1"
#500000
0"
#505000
1"
#510000
0"
b1010 $
b1010 %
#515000
1"
#520000
0"
#525000
1"
#530000
0"
#535000
1"
#540000
0"
#545000
1"
#550000
0"
#555000
1"
#560000
0"
#565000
1"
#570000
0"
#575000
1"
#580000
0"
#585000
1"
#590000
0"
#595000
1"
#600000
0"
#605000
1"
#610000
0"
b110010 $
b110010 %
#615000
1"
#620000
0"
#625000
1"
#630000
0"
#635000
1"
#640000
0"
#645000
1"
#650000
0"
#655000
1"
#660000
0"
#665000
1"
#670000
0"
#675000
1"
#680000
0"
#685000
1"
#690000
0"
#695000
1"
#700000
0"
#705000
1"
#710000
0"
b1100100 $
b1100100 %
#715000
1"
#720000
0"
#725000
1"
#730000
0"
b1010001 $
b1010001 %
#735000
1"
#740000
0"
#745000
1"
#750000
0"
b100100 $
b100100 %
