experiment/cordic_trig_8bit.v
module cordic_trig(
    input wire clk,
    input wire rst,
    input wire [7:0] angle,     // Input angle in range 0-255 (0 to 2π)
    output reg [7:0] sine,      // Scaled sine output
    output reg [7:0] cosine     // Scaled cosine output
);

    // Constants for CORDIC angles (atan values)
    reg [7:0] atan_table [0:7];
    initial begin
        atan_table[0] = 8'd64;  // atan(1)    ≈ 45°
        atan_table[1] = 8'd38;  // atan(1/2)  ≈ 26.57°
        atan_table[2] = 8'd20;  // atan(1/4)  ≈ 14.04°
        atan_table[3] = 8'd10;  // atan(1/8)  ≈ 7.13°
        atan_table[4] = 8'd5;   // atan(1/16) ≈ 3.58°
        atan_table[5] = 8'd3;   // atan(1/32) ≈ 1.79°
        atan_table[6] = 8'd1;   // atan(1/64) ≈ 0.89°
        atan_table[7] = 8'd1;   // atan(1/128)≈ 0.45°
    end

    // Internal registers
    reg [8:0] x, x_next;
    reg [8:0] y, y_next;
    reg [7:0] z, z_next;
    reg [3:0] iteration;
    
    // CORDIC scaling factor compensation (K ≈ 0.607)
    parameter SCALE = 8'd78;    // 0.607 * 128

    always @(posedge clk or posedge rst) begin
        if (rst) begin
            x <= SCALE;         // Initialize with scaling factor
            y <= 9'd0;
            z <= angle;
            iteration <= 4'd0;
        end else if (iteration < 8) begin
            // Determine rotation direction
            if (z[7]) begin     // Negative angle
                x_next = x + (y >>> iteration);
                y_next = y - (x >>> iteration);
                z_next = z + atan_table[iteration];
            end else begin      // Positive angle
                x_next = x - (y >>> iteration);
                y_next = y + (x >>> iteration);
                z_next = z - atan_table[iteration];
            end
            
            x <= x_next;
            y <= y_next;
            z <= z_next;
            iteration <= iteration + 1;
        end
        
        // Output scaled results
        cosine <= x[8:1];      // Scale down and take upper bits
        sine <= y[8:1];        // Scale down and take upper bits
    end
endmodule

experiment/cordic_trig_8bit_tb.v
module cordic_trig_tb;
    reg clk;
    reg rst;
    reg [7:0] angle;
    wire [7:0] sine;
    wire [7:0] cosine;
    
    // Instantiate the CORDIC trigonometric module
    cordic_trig uut (
        .clk(clk),
        .rst(rst),
        .angle(angle),
        .sine(sine),
        .cosine(cosine)
    );
    
    // Clock generation
    initial begin
        clk = 0;
        forever #5 clk = ~clk;
    end
    
    // Test stimulus
    initial begin
        $dumpfile("cordic_trig.vcd");
        $dumpvars(0, cordic_trig_tb);
        
        // Test case 1: Reset
        rst = 1;
        angle = 8'd0;
        #10;
        rst = 0;
        #100;
        
        // Test case 2: 0 degrees (0)
        angle = 8'd0;
        #100;
        
        // Test case 3: 90 degrees (64)
        angle = 8'd64;
        #100;
        
        // Test case 4: 180 degrees (128)
        angle = 8'd128;
        #100;
        
        // Test case 5: 270 degrees (192)
        angle = 8'd192;
        #100;
        
        // Test case 6: 45 degrees (32)
        angle = 8'd32;
        #100;
        
        $display("All tests completed");
        $finish;
    end
    
    // Monitor changes
    // initial begin
    //     $monitor("Time=%0t angle=%d sine=%d cosine=%d", 
    //             $time, angle, $signed(sine), $signed(cosine));
    // end
endmodule

experiment/cordic_trig.vcd
$date
	Mon Nov 25 16:43:39 2024
$end
$version
	Icarus Verilog
$end
$timescale
	1s
$end
$scope module cordic_trig_tb $end
$var wire 8 ! sine [7:0] $end
$var wire 8 " cosine [7:0] $end
$var reg 8 # angle [7:0] $end
$var reg 1 $ clk $end
$var reg 1 % rst $end
$scope module uut $end
$var wire 8 & angle [7:0] $end
$var wire 1 $ clk $end
$var wire 1 % rst $end
$var parameter 8 ' SCALE $end
$var reg 8 ( cosine [7:0] $end
$var reg 4 ) iteration [3:0] $end
$var reg 8 * sine [7:0] $end
$var reg 9 + x [8:0] $end
$var reg 9 , x_next [8:0] $end
$var reg 9 - y [8:0] $end
$var reg 9 . y_next [8:0] $end
$var reg 8 / z [7:0] $end
$var reg 8 0 z_next [7:0] $end
$upscope $end
$upscope $end
$enddefinitions $end
$comment Show the parameter values. $end
$dumpall
b1001110 '
$end
#0
$dumpvars
bx 0
b0 /
bx .
b0 -
bx ,
b1001110 +
bx *
b0 )
bx (
b0 &
1%
0$
b0 #
bx "
bx !
$end
#5
b0 !
b0 *
b100111 "
b100111 (
1$
#10
0$
0%
#15
b1 )
b11000000 /
b1001110 -
b11000000 0
b1001110 .
b1001110 ,
1$
#20
0$
#25
b100111 !
b100111 *
b10 )
b11100110 /
b100111 -
b1110101 +
b11100110 0
b100111 .
b1110101 ,
1$
#30
0$
#35
b10011 !
b10011 *
b111010 "
b111010 (
b11 )
b11111010 /
b1010 -
b1111110 +
b11111010 0
b1010 .
b1111110 ,
1$
#40
0$
#45
b101 !
b101 *
b111111 "
b111111 (
b100 )
b100 /
b111111011 -
b1111111 +
b100 0
b111111011 .
b1111111 ,
1$
#50
0$
#55
b11111101 !
b11111101 *
b101 )
b11111111 /
b10 -
b1100000 +
b11111111 0
b10 .
b1100000 ,
1$
#60
0$
#65
b1 !
b1 *
b110000 "
b110000 (
b110 )
b10 /
b111111111 -
b10 0
b111111111 .
1$
#70
0$
#75
b11111111 !
b11111111 *
b111 )
b1 /
b0 -
b1011001 +
b1 0
b0 .
b1011001 ,
1$
#80
0$
#85
b0 !
b0 *
b101100 "
b101100 (
b1000 )
b0 /
b0 0
1$
#90
0$
#95
1$
#100
0$
#105
1$
#110
0$
#115
1$
#120
0$
#125
1$
#130
0$
#135
1$
#140
0$
#145
1$
#150
0$
#155
1$
#160
0$
#165
1$
#170
0$
#175
1$
#180
0$
#185
1$
#190
0$
#195
1$
#200
0$
#205
1$
#210
0$
b1000000 #
b1000000 &
#215
1$
#220
0$
#225
1$
#230
0$
#235
1$
#240
0$
#245
1$
#250
0$
#255
1$
#260
0$
#265
1$
#270
0$
#275
1$
#280
0$
#285
1$
#290
0$
#295
1$
#300
0$
#305
1$
#310
0$
b10000000 #
b10000000 &
#315
1$
#320
0$
#325
1$
#330
0$
#335
1$
#340
0$
#345
1$
#350
0$
#355
1$
#360
0$
#365
1$
#370
0$
#375
1$
#380
0$
#385
1$
#390
0$
#395
1$
#400
0$
#405
1$
#410
0$
b11000000 #
b11000000 &
#415
1$
#420
0$
#425
1$
#430
0$
#435
1$
#440
0$
#445
1$
#450
0$
#455
1$
#460
0$
#465
1$
#470
0$
#475
1$
#480
0$
#485
1$
#490
0$
#495
1$
#500
0$
#505
1$
#510
0$
b100000 #
b100000 &
