experiment/div_mod_3.v
/*
Division by 3 Circuit (div_mod_3.v)

This Verilog module implements a digital circuit that divides an 8-bit number by 3 and produces both the quotient and remainder. Let's break it down in simple terms.

Purpose: The circuit performs division by 3 on any number between 0 and 255 (8 bits) and tells you both how many times 3 goes into that number (quotient) and what's left over (remainder).

Inputs and Outputs:

- Input: An 8-bit number 'n' that you want to divide by 3
- Outputs:
    - An 8-bit quotient (how many times 3 goes into n)
    - A 2-bit remainder (what's left over, which can only be 0, 1, or 2)

How it works: The circuit uses a clever method that breaks down the division process into four iterations. Instead of doing regular division, it uses a series of additions and bit manipulations. Here's the step-by-step process:

1. First iteration: It splits the input number into two parts and adds them together
2. Second iteration: Takes the result from step 1, splits it again, and adds those parts
3. Third iteration: Repeats the process with the result from step 2
4. Fourth iteration: Does one final split and add operation

The final step checks if the last remainder equals 3 (binary '11'). If it does, it adds 1 to the quotient and sets the remainder to 0, because if we have a remainder of 3, that means we can fit in one more complete division by 3.

The beauty of this design is that it avoids complex division operations by using simpler operations like addition and bit selection. This makes it efficient to implement in digital hardware. The circuit processes all these steps simultaneously (in parallel) since it uses wires rather than sequential operations.

This is particularly useful in digital systems where you need to perform division by 3 quickly and efficiently, such as in digital signal processing or certain types of data encoding.
*/
module div_mod_3(
    input wire [7:0] n,
    output wire [7:0] quotient,
    output wire [1:0] remainder
);
    // First iteration
    wire [5:0] q1 = n[7:2];
    wire [1:0] r1 = n[1:0];
    wire [6:0] rem1 = q1 + r1;

    // Second iteration
    wire [4:0] q2 = rem1[6:2];
    wire [1:0] r2 = rem1[1:0];
    wire [5:0] rem2 = q2 + r2;

    // Third iteration
    wire [3:0] q3 = rem2[5:2];
    wire [1:0] r3 = rem2[1:0];
    wire [4:0] rem3 = q3 + r3;

    // Fourth iteration
    wire [1:0] q4 = rem3[4:2];
    wire [1:0] r4 = rem3[1:0];
    wire [1:0] rem4 = q4 + r4;

    // Final quotient sum
    wire [7:0] quotient_sum = q1 + q2 + q3 + q4;

    // Final check and output assignment
    assign quotient = (rem4 == 2'b11) ? quotient_sum + 1 : quotient_sum;
    assign remainder = (rem4 == 2'b11) ? 2'b00 : rem4[1:0];
endmodule

experiment/tests/test_div_mod_3.v
`timescale 1ns/1ps

module test_div_mod_3;
    reg [7:0] n;
    wire [7:0] quotient;
    wire [1:0] remainder;

    div_mod_3 dut (
        .n(n),
        .quotient(quotient),
        .remainder(remainder)
    );

    initial begin
        // Test case 1: Basic division by 3
        n = 8'd9;
        #10;
        if (quotient !== 8'd3 || remainder !== 2'd0) $error("Test 1 failed");

        // Test case 2: Number with remainder 1
        n = 8'd10;
        #10;
        if (quotient !== 8'd3 || remainder !== 2'd1) $error("Test 2 failed");

        // Test case 3: Number with remainder 2
        n = 8'd11;
        #10;
        if (quotient !== 8'd3 || remainder !== 2'd2) $error("Test 3 failed");

        // Test case 4: Maximum input
        n = 8'd255;
        #10;
        if (quotient !== 8'd85 || remainder !== 2'd0) $error("Test 4 failed");

        // Test case 5: Zero input
        n = 8'd0;
        #10;
        if (quotient !== 8'd0 || remainder !== 2'd0) $error("Test 5 failed");

        // Test case 6: Small number less than 3
        n = 8'd2;
        #10;
        if (quotient !== 8'd0 || remainder !== 2'd2) $error("Test 6 failed");

        // Test case 7: Large number with remainder
        n = 8'd250;
        #10;
        if (quotient !== 8'd83 || remainder !== 2'd1) $error("Test 7 failed");

        // Test case 8: Multiple of 3
        n = 8'd99;
        #10;
        if (quotient !== 8'd33 || remainder !== 2'd0) $error("Test 8 failed");

        $display("All tests completed");
        $finish;
    end

    initial begin
        $dumpfile("test_div_mod_3.vcd");
        $dumpvars(0, test_div_mod_3);
    end
endmodule

experiment/test_div_mod_3.vcd
$date
	Mon Nov 18 16:43:06 2024
$end
$version
	Icarus Verilog
$end
$timescale
	1ps
$end
$scope module test_div_mod_3 $end
$var wire 2 ! remainder [1:0] $end
$var wire 8 " quotient [7:0] $end
$var reg 8 # n [7:0] $end
$scope module dut $end
$var wire 8 $ n [7:0] $end
$var wire 2 % remainder [1:0] $end
$var wire 2 & rem4 [1:0] $end
$var wire 5 ' rem3 [4:0] $end
$var wire 6 ( rem2 [5:0] $end
$var wire 7 ) rem1 [6:0] $end
$var wire 2 * r4 [1:0] $end
$var wire 2 + r3 [1:0] $end
$var wire 2 , r2 [1:0] $end
$var wire 2 - r1 [1:0] $end
$var wire 8 . quotient_sum [7:0] $end
$var wire 8 / quotient [7:0] $end
$var wire 2 0 q4 [1:0] $end
$var wire 4 1 q3 [3:0] $end
$var wire 5 2 q2 [4:0] $end
$var wire 6 3 q1 [5:0] $end
$upscope $end
$upscope $end
$enddefinitions $end
$comment Show the parameter values. $end
$dumpall
$end
#0
$dumpvars
b10 3
b0 2
b0 1
b0 0
b11 /
b10 .
b1 -
b11 ,
b11 +
b11 *
b11 )
b11 (
b11 '
b11 &
b0 %
b1001 $
b1001 #
b11 "
b0 !
$end
#10000
b1 !
b1 %
b1 &
b1 *
b11 "
b11 /
b1 '
b1 +
b11 .
b1 2
b1 (
b0 ,
b100 )
b10 -
b1010 #
b1010 $
#20000
b10 !
b10 %
b10 &
b10 *
b10 '
b10 +
b10 (
b1 ,
b101 )
b11 -
b1011 #
b1011 $
#30000
b0 !
b0 %
b11 &
b1 0
b110 '
b100 1
b10000 2
b10010 (
b10 ,
b1010101 "
b1010101 /
b1000010 )
b1010100 .
b111111 3
b11111111 #
b11111111 $
#40000
b0 0
b0 !
b0 %
b0 &
b0 *
b0 1
b0 '
b0 +
b0 "
b0 /
b0 2
b0 (
b0 ,
b0 .
b0 3
b0 )
b0 -
b0 #
b0 $
#50000
b10 !
b10 %
b10 &
b10 *
b10 '
b10 +
b10 (
b10 ,
b10 )
b10 -
b10 #
b10 $
#60000
b1 0
b1 !
b1 %
b1 &
b0 *
b100 1
b100 '
b0 +
b10000 2
b10000 (
b0 ,
b1010011 "
b1010011 /
b1000000 )
b1010011 .
b111110 3
b11111010 #
b11111010 $
#70000
b0 0
b0 !
b0 %
b11 &
b11 *
b10 1
b11 '
b1 +
b110 2
b100001 "
b100001 /
b1001 (
b11 ,
b100000 .
b11000 3
b11011 )
b11 -
b1100011 #
b1100011 $
