hwdesign/div_mod_7.v
/*
This Verilog module implements a digital circuit that divides a 9-bit number by 7 and produces both the quotient and remainder. Think of it like a specialized calculator that can only do division by 7.

The circuit takes one input: a 9-bit number 'n' (which can represent values from 0 to 511). It produces two outputs: a 9-bit 'quotient' (the result of dividing n by 7) and a 3-bit 'remainder' (what's left over after the division).

The algorithm works through a clever iterative process that avoids actual division operations (which are complex in digital hardware). Instead, it uses three stages of simpler additions:

In the first stage, it splits the input number into two parts: the upper 6 bits (q1) and lower 3 bits (r1), then adds them together. The second stage takes this result and again splits it into upper bits (q2) and lower bits (r2), adding them together. The third stage does one final split and addition with q3 and r3.

The final step combines all the quotient parts (q1 + q2 + q3) and checks if the remainder needs adjustment. If the remainder equals 7 (binary 111), it increases the quotient by 1 and sets the remainder to 0, since having a remainder of 7 means we can fit in one more complete division by 7.

This method is based on a mathematical property where dividing by 7 can be done through repeated additions of smaller parts, making it much simpler to implement in digital hardware than traditional division. The circuit effectively transforms what would be a complex division operation into a series of simpler additions and bit manipulations.
*/
module div_mod_7(
    input wire [8:0] n,
    output wire [8:0] quotient,
    output wire [2:0] remainder
);
    // First iteration
    wire [5:0] q1 = n[8:3];
    wire [2:0] r1 = n[2:0];
    wire [6:0] rem1 = q1 + r1;

    // Second iteration
    wire [3:0] q2 = rem1[6:3];
    wire [2:0] r2 = rem1[2:0];
    wire [4:0] rem2 = q2 + r2;

    // Third iteration
    wire [1:0] q3 = rem2[4:3];
    wire [2:0] r3 = rem2[2:0];
    wire [2:0] rem3 = q3 + r3;

    // Final quotient sum
    wire [7:0] quotient_sum = q1 + q2 + q3;

    // Final check and output assignment
    assign quotient = (rem3 == 3'b111) ? quotient_sum + 1 : quotient_sum;
    assign remainder = (rem3 == 3'b111) ? 3'b000 : rem3[2:0];
endmodule

hwdesign/div_mod_3.v
/*
Division by 3 Circuit (div_mod_3.v)

This Verilog module implements a digital circuit that divides an 8-bit number by 3 and produces both the quotient and remainder. Let's break it down in simple terms.

Purpose: The circuit performs division by 3 on any number between 0 and 255 (8 bits) and tells you both how many times 3 goes into that number (quotient) and what's left over (remainder).

Inputs and Outputs:

- Input: An 8-bit number 'n' that you want to divide by 3
- Outputs:
    - An 8-bit quotient (how many times 3 goes into n)
    - A 2-bit remainder (what's left over, which can only be 0, 1, or 2)

How it works: The circuit uses a clever method that breaks down the division process into four iterations. Instead of doing regular division, it uses a series of additions and bit manipulations. Here's the step-by-step process:

1. First iteration: It splits the input number into two parts and adds them together
2. Second iteration: Takes the result from step 1, splits it again, and adds those parts
3. Third iteration: Repeats the process with the result from step 2
4. Fourth iteration: Does one final split and add operation

The final step checks if the last remainder equals 3 (binary '11'). If it does, it adds 1 to the quotient and sets the remainder to 0, because if we have a remainder of 3, that means we can fit in one more complete division by 3.

The beauty of this design is that it avoids complex division operations by using simpler operations like addition and bit selection. This makes it efficient to implement in digital hardware. The circuit processes all these steps simultaneously (in parallel) since it uses wires rather than sequential operations.

This is particularly useful in digital systems where you need to perform division by 3 quickly and efficiently, such as in digital signal processing or certain types of data encoding.
*/
module div_mod_3(
    input wire [7:0] n,
    output wire [7:0] quotient,
    output wire [1:0] remainder
);
    // First iteration
    wire [5:0] q1 = n[7:2];
    wire [1:0] r1 = n[1:0];
    wire [6:0] rem1 = q1 + r1;

    // Second iteration
    wire [4:0] q2 = rem1[6:2];
    wire [1:0] r2 = rem1[1:0];
    wire [5:0] rem2 = q2 + r2;

    // Third iteration
    wire [3:0] q3 = rem2[5:2];
    wire [1:0] r3 = rem2[1:0];
    wire [4:0] rem3 = q3 + r3;

    // Fourth iteration
    wire [1:0] q4 = rem3[4:2];
    wire [1:0] r4 = rem3[1:0];
    wire [1:0] rem4 = q4 + r4;

    // Final quotient sum
    wire [7:0] quotient_sum = q1 + q2 + q3 + q4;

    // Final check and output assignment
    assign quotient = (rem4 == 2'b11) ? quotient_sum + 1 : quotient_sum;
    assign remainder = (rem4 == 2'b11) ? 2'b00 : rem4[1:0];
endmodule

hwdesign/vdcorput_fsm_32bit_simple.v
/*
VdCorput FSM-Based Sequential Implementation (32-bit) - Simple Verilog Version
Supports bases 2, 3, and 7

This module implements the Van der Corput sequence generator using a Finite State Machine (FSM) approach.
Simplified for iverilog compatibility.
*/

module vdcorput_fsm_32bit_simple (
    input clk,
    input rst_n,
    input start,
    input [31:0] k_in,
    input [1:0] base_sel,
    output reg [31:0] result,
    output reg done,
    output reg ready
);

    // FSM states
    parameter IDLE = 3'b000;
    parameter INIT = 3'b001;
    parameter DIVIDE = 3'b010;
    parameter ACCUMULATE = 3'b011;
    parameter UPDATE = 3'b100;
    parameter CHECK = 3'b101;
    parameter FINISH = 3'b110;

    reg [2:0] current_state, next_state;

    // Internal registers
    reg [31:0] k_reg;          // Current k value
    reg [31:0] power_reg;      // Current power of base (1/base^i in fixed-point)
    reg [31:0] acc_reg;        // Accumulator for result
    reg [31:0] base_reg;       // Current base value
    reg [31:0] remainder_reg;  // Remainder from division
    reg [31:0] quotient_reg;   // Quotient from division

    // Fixed-point constants (16.16 format)
    parameter FP_ONE = 32'h00010000;  // 1.0 in fixed-point
    parameter FP_HALF = 32'h00008000; // 0.5 in fixed-point
    parameter FP_THIRD = 32'h00005555; // 1/3 ≈ 0.3333 in fixed-point
    parameter FP_SEVENTH = 32'h00002492; // 1/7 ≈ 0.142857 in fixed-point

    // Division modules for bases 3 and 7
    wire [7:0] div3_quotient;
    wire [8:0] div7_quotient;
    wire [1:0] div3_remainder;
    wire [2:0] div7_remainder;

    // Instantiate division modules
    div_mod_3 div3_inst (
        .n(k_reg[7:0]),  // Use lower 8 bits for division by 3
        .quotient(div3_quotient),
        .remainder(div3_remainder)
    );

    div_mod_7 div7_inst (
        .n(k_reg[8:0]),  // Use lower 9 bits for division by 7
        .quotient(div7_quotient),
        .remainder(div7_remainder)
    );

    // FSM state transition
    always @(posedge clk or negedge rst_n) begin
        if (!rst_n) begin
            current_state <= IDLE;
        end else begin
            current_state <= next_state;
        end
    end

    // FSM next state logic
    always @(*) begin
        next_state = current_state;
        case (current_state)
            IDLE: begin
                if (start) next_state = INIT;
            end
            INIT: next_state = DIVIDE;
            DIVIDE: next_state = ACCUMULATE;
            ACCUMULATE: next_state = UPDATE;
            UPDATE: next_state = CHECK;
            CHECK: begin
                if (k_reg == 0) next_state = FINISH;
                else next_state = DIVIDE;
            end
            FINISH: next_state = IDLE;
            default: next_state = IDLE;
        endcase
    end

    // FSM output logic and register updates
    always @(posedge clk or negedge rst_n) begin
        if (!rst_n) begin
            k_reg <= 0;
            power_reg <= FP_ONE;
            acc_reg <= 0;
            base_reg <= 2;
            remainder_reg <= 0;
            quotient_reg <= 0;
            result <= 0;
            done <= 0;
            ready <= 1;
        end else begin
            case (current_state)
                IDLE: begin
                    ready <= 1;
                    done <= 0;
                    if (start) begin
                        ready <= 0;
                        // Store input values
                        k_reg <= k_in;
                    end
                end
                INIT: begin
                    // Initialize registers based on base selection
                    case (base_sel)
                        2'b00: begin  // Base 2
                            base_reg <= 2;
                            power_reg <= FP_HALF;  // 1/2
                        end
                        2'b01: begin  // Base 3
                            base_reg <= 3;
                            power_reg <= FP_THIRD;  // 1/3
                        end
                        2'b10: begin  // Base 7
                            base_reg <= 7;
                            power_reg <= FP_SEVENTH;  // 1/7
                        end
                        default: begin  // Default to base 2
                            base_reg <= 2;
                            power_reg <= FP_HALF;
                        end
                    endcase
                    acc_reg <= 0;
                end
                DIVIDE: begin
                    // Perform division based on base
                    case (base_reg)
                        2: begin  // Base 2 - simple shift
                            quotient_reg <= k_reg >> 1;
                            remainder_reg <= k_reg[0];
                        end
                        3: begin  // Base 3 - use division module
                            quotient_reg <= {24'b0, div3_quotient};
                            remainder_reg <= {30'b0, div3_remainder};
                        end
                        7: begin  // Base 7 - use division module
                            quotient_reg <= {23'b0, div7_quotient};
                            remainder_reg <= {29'b0, div7_remainder};
                        end
                        default: begin  // Should not happen
                            quotient_reg <= 0;
                            remainder_reg <= 0;
                        end
                    endcase
                end
                ACCUMULATE: begin
                    // Accumulate remainder * power_of_base
                    if (remainder_reg != 0) begin
                        // Fixed-point multiplication: remainder * power_reg
                        // Since remainder is small (0-6), we can use simple multiplication
                        acc_reg <= acc_reg + (remainder_reg * power_reg);
                    end
                end
                UPDATE: begin
                    // Update k and power_of_base
                    k_reg <= quotient_reg;
                    // power_reg = power_reg / base_reg (fixed-point division)
                    case (base_reg)
                        2: power_reg <= power_reg >> 1;  // Divide by 2
                        3: power_reg <= (power_reg * FP_THIRD) >> 16;  // Multiply by 1/3
                        7: power_reg <= (power_reg * FP_SEVENTH) >> 16;  // Multiply by 1/7
                    endcase
                end
                CHECK: begin
                    // k_reg already updated in UPDATE state
                    // Nothing to do here, FSM handles transition
                end
                FINISH: begin
                    result <= acc_reg;
                    done <= 1;
                end
            endcase
        end
    end

endmodule

hwdesign/vdcorput_fsm_32bit_simple_tb.v
/*
Testbench for VdCorput FSM-Based Sequential Implementation (32-bit) - Simple Version
*/

`timescale 1ns/1ps

module vdcorput_fsm_32bit_simple_tb;

    // Parameters
    parameter CLK_PERIOD = 10;  // 10ns = 100MHz

    // Test vectors for base 2 (16.16 fixed-point)
    reg [31:0] test_vectors_base2_k [0:5];
    reg [31:0] test_vectors_base2_expected [0:5];
    
    // Test vectors for base 3 (16.16 fixed-point)
    reg [31:0] test_vectors_base3_k [0:5];
    reg [31:0] test_vectors_base3_expected [0:5];
    
    // Test vectors for base 7 (16.16 fixed-point)
    reg [31:0] test_vectors_base7_k [0:5];
    reg [31:0] test_vectors_base7_expected [0:5];

    // Signals
    reg clk;
    reg rst_n;
    reg start;
    reg [31:0] k_in;
    reg [1:0] base_sel;
    wire [31:0] result;
    wire done;
    wire ready;

    // Test control
    integer test_index;
    integer error_count;
    integer total_tests;
    integer test_passed;
    integer test_failed;

    // Instantiate DUT
    vdcorput_fsm_32bit_simple dut (
        .clk(clk),
        .rst_n(rst_n),
        .start(start),
        .k_in(k_in),
        .base_sel(base_sel),
        .result(result),
        .done(done),
        .ready(ready)
    );

    // Clock generation
    always begin
        #(CLK_PERIOD/2) clk = ~clk;
    end

    // Initialize test vectors
    initial begin
        // Base 2 test vectors
        test_vectors_base2_k[0] = 32'd1;  test_vectors_base2_expected[0] = 32'h00008000;  // 0.5
        test_vectors_base2_k[1] = 32'd2;  test_vectors_base2_expected[1] = 32'h00004000;  // 0.25
        test_vectors_base2_k[2] = 32'd3;  test_vectors_base2_expected[2] = 32'h0000C000;  // 0.75
        test_vectors_base2_k[3] = 32'd4;  test_vectors_base2_expected[3] = 32'h00002000;  // 0.125
        test_vectors_base2_k[4] = 32'd5;  test_vectors_base2_expected[4] = 32'h0000A000;  // 0.625
        test_vectors_base2_k[5] = 32'd11; test_vectors_base2_expected[5] = 32'h0000D000;  // 0.8125
        
        // Base 3 test vectors
        test_vectors_base3_k[0] = 32'd1;  test_vectors_base3_expected[0] = 32'h00005555;  // 0.333333
        test_vectors_base3_k[1] = 32'd2;  test_vectors_base3_expected[1] = 32'h0000AAAA;  // 0.666667
        test_vectors_base3_k[2] = 32'd3;  test_vectors_base3_expected[2] = 32'h00001C71;  // 0.111111
        test_vectors_base3_k[3] = 32'd4;  test_vectors_base3_expected[3] = 32'h000071C7;  // 0.444444
        test_vectors_base3_k[4] = 32'd5;  test_vectors_base3_expected[4] = 32'h0000C71C;  // 0.777778
        test_vectors_base3_k[5] = 32'd11; test_vectors_base3_expected[5] = 32'h0000B425;  // 0.703704
        
        // Base 7 test vectors
        test_vectors_base7_k[0] = 32'd1;  test_vectors_base7_expected[0] = 32'h00002492;  // 0.142857
        test_vectors_base7_k[1] = 32'd2;  test_vectors_base7_expected[1] = 32'h00004924;  // 0.285714
        test_vectors_base7_k[2] = 32'd3;  test_vectors_base7_expected[2] = 32'h00006DB6;  // 0.428571
        test_vectors_base7_k[3] = 32'd4;  test_vectors_base7_expected[3] = 32'h00009249;  // 0.571429
        test_vectors_base7_k[4] = 32'd5;  test_vectors_base7_expected[4] = 32'h0000B6DB;  // 0.714286
        test_vectors_base7_k[5] = 32'd11; test_vectors_base7_expected[5] = 32'h00009782;  // 0.591837
    end

    // Test task for a single test vector
    task run_test;
        input [31:0] k_val;
        input [1:0] base_val;
        input [31:0] expected_val;
        begin
            // Wait for module to be ready
            wait(ready == 1'b1);
            @(posedge clk);
            
            // Apply test vector
            k_in = k_val;
            base_sel = base_val;
            start = 1'b1;
            
            @(posedge clk);
            start = 1'b0;
            
            // Wait for computation to complete
            wait(done == 1'b1);
            @(posedge clk);
            
            // Check result with tolerance
            if (result >= expected_val - 32'h00000100 && result <= expected_val + 32'h00000100) begin
                $display("PASS: k=%0d, base_sel=%b, expected=0x%08h, got=0x%08h", 
                         k_val, base_val, expected_val, result);
                test_passed = test_passed + 1;
            end else begin
                $display("FAIL: k=%0d, base_sel=%b, expected=0x%08h, got=0x%08h", 
                         k_val, base_val, expected_val, result);
                test_failed = test_failed + 1;
                error_count = error_count + 1;
            end
            
            total_tests = total_tests + 1;
        end
    endtask

    // Main test sequence
    initial begin
        // Initialize
        clk = 0;
        rst_n = 0;
        start = 0;
        k_in = 0;
        base_sel = 0;
        test_index = 0;
        error_count = 0;
        total_tests = 0;
        test_passed = 0;
        test_failed = 0;
        
        // Apply reset
        #(CLK_PERIOD * 2);
        rst_n = 1;
        #(CLK_PERIOD * 2);
        
        $display("==========================================");
        $display("Starting VdCorput FSM Testbench (Simple)");
        $display("==========================================");
        
        // Test Base 2
        $display("\nTesting Base 2:");
        $display("----------------");
        for (test_index = 0; test_index < 6; test_index = test_index + 1) begin
            run_test(test_vectors_base2_k[test_index], 2'b00, test_vectors_base2_expected[test_index]);
        end
        
        // Test Base 3
        $display("\nTesting Base 3:");
        $display("----------------");
        for (test_index = 0; test_index < 6; test_index = test_index + 1) begin
            run_test(test_vectors_base3_k[test_index], 2'b01, test_vectors_base3_expected[test_index]);
        end
        
        // Test Base 7
        $display("\nTesting Base 7:");
        $display("----------------");
        for (test_index = 0; test_index < 6; test_index = test_index + 1) begin
            run_test(test_vectors_base7_k[test_index], 2'b10, test_vectors_base7_expected[test_index]);
        end
        
        // Summary
        $display("\n==========================================");
        $display("Test Summary:");
        $display("  Total tests: %0d", total_tests);
        $display("  Passed: %0d", test_passed);
        $display("  Failed: %0d", test_failed);
        $display("  Error count: %0d", error_count);
        
        if (error_count == 0) begin
            $display("\nAll tests PASSED!");
        end else begin
            $display("\nSome tests FAILED!");
        end
        
        $display("==========================================");
        
        // Finish simulation
        #(CLK_PERIOD * 10);
        $finish;
    end

    // Dump VCD file for waveform viewing
    initial begin
        $dumpfile("vdcorput_fsm_32bit_simple_tb.vcd");
        $dumpvars(0, vdcorput_fsm_32bit_simple_tb);
    end

endmodule

hwdesign/vdcorput_fsm_32bit_simple_tb.vcd
$date
	Mon Dec 08 10:48:24 2025
$end
$version
	Icarus Verilog
$end
$timescale
	1ps
$end
$scope module vdcorput_fsm_32bit_simple_tb $end
$var wire 32 ! result [31:0] $end
$var wire 1 " ready $end
$var wire 1 # done $end
$var parameter 32 $ CLK_PERIOD $end
$var reg 2 % base_sel [1:0] $end
$var reg 1 & clk $end
$var reg 32 ' k_in [31:0] $end
$var reg 1 ( rst_n $end
$var reg 1 ) start $end
$var integer 32 * error_count [31:0] $end
$var integer 32 + test_failed [31:0] $end
$var integer 32 , test_index [31:0] $end
$var integer 32 - test_passed [31:0] $end
$var integer 32 . total_tests [31:0] $end
$scope module dut $end
$var wire 2 / base_sel [1:0] $end
$var wire 1 & clk $end
$var wire 32 0 k_in [31:0] $end
$var wire 1 ( rst_n $end
$var wire 1 ) start $end
$var wire 3 1 div7_remainder [2:0] $end
$var wire 9 2 div7_quotient [8:0] $end
$var wire 2 3 div3_remainder [1:0] $end
$var wire 8 4 div3_quotient [7:0] $end
$var parameter 3 5 ACCUMULATE $end
$var parameter 3 6 CHECK $end
$var parameter 3 7 DIVIDE $end
$var parameter 3 8 FINISH $end
$var parameter 32 9 FP_HALF $end
$var parameter 32 : FP_ONE $end
$var parameter 32 ; FP_SEVENTH $end
$var parameter 32 < FP_THIRD $end
$var parameter 3 = IDLE $end
$var parameter 3 > INIT $end
$var parameter 3 ? UPDATE $end
$var reg 32 @ acc_reg [31:0] $end
$var reg 32 A base_reg [31:0] $end
$var reg 3 B current_state [2:0] $end
$var reg 1 # done $end
$var reg 32 C k_reg [31:0] $end
$var reg 3 D next_state [2:0] $end
$var reg 32 E power_reg [31:0] $end
$var reg 32 F quotient_reg [31:0] $end
$var reg 1 " ready $end
$var reg 32 G remainder_reg [31:0] $end
$var reg 32 H result [31:0] $end
$scope module div3_inst $end
$var wire 8 I n [7:0] $end
$var wire 2 J remainder [1:0] $end
$var wire 2 K rem4 [1:0] $end
$var wire 5 L rem3 [4:0] $end
$var wire 6 M rem2 [5:0] $end
$var wire 7 N rem1 [6:0] $end
$var wire 2 O r4 [1:0] $end
$var wire 2 P r3 [1:0] $end
$var wire 2 Q r2 [1:0] $end
$var wire 2 R r1 [1:0] $end
$var wire 8 S quotient_sum [7:0] $end
$var wire 8 T quotient [7:0] $end
$var wire 2 U q4 [1:0] $end
$var wire 4 V q3 [3:0] $end
$var wire 5 W q2 [4:0] $end
$var wire 6 X q1 [5:0] $end
$upscope $end
$scope module div7_inst $end
$var wire 9 Y n [8:0] $end
$var wire 3 Z remainder [2:0] $end
$var wire 3 [ rem3 [2:0] $end
$var wire 5 \ rem2 [4:0] $end
$var wire 7 ] rem1 [6:0] $end
$var wire 3 ^ r3 [2:0] $end
$var wire 3 _ r2 [2:0] $end
$var wire 3 ` r1 [2:0] $end
$var wire 8 a quotient_sum [7:0] $end
$var wire 9 b quotient [8:0] $end
$var wire 2 c q3 [1:0] $end
$var wire 4 d q2 [3:0] $end
$var wire 6 e q1 [5:0] $end
$upscope $end
$upscope $end
$scope task run_test $end
$var reg 2 f base_val [1:0] $end
$var reg 32 g expected_val [31:0] $end
$var reg 32 h k_val [31:0] $end
$upscope $end
$upscope $end
$enddefinitions $end
$comment Show the parameter values. $end
$dumpall
b100 ?
b1 >
b0 =
b101010101010101 <
b10010010010010 ;
b10000000000000000 :
b1000000000000000 9
b110 8
b10 7
b101 6
b11 5
b1010 $
$end
#0
$dumpvars
bx h
bx g
bx f
b0 e
b0 d
b0 c
b0 b
b0 a
b0 `
b0 _
b0 ^
b0 ]
b0 \
b0 [
b0 Z
b0 Y
b0 X
b0 W
b0 V
b0 U
b0 T
b0 S
b0 R
b0 Q
b0 P
b0 O
b0 N
b0 M
b0 L
b0 K
b0 J
b0 I
b0 H
b0 G
b0 F
b10000000000000000 E
b0 D
b0 C
b0 B
b10 A
b0 @
b0 4
b0 3
b0 2
b0 1
b0 0
b0 /
b0 .
b0 -
b0 ,
b0 +
b0 *
0)
0(
b0 '
0&
b0 %
0#
1"
b0 !
$end
#5000
1&
#10000
0&
#15000
1&
#20000
0&
1(
#25000
1&
#30000
0&
#35000
1&
#40000
0&
b1000000000000000 g
b0 f
b1 h
#45000
b1 3
b1 J
b1 K
b1 O
b1 1
b1 Z
b1 L
b1 P
b1 [
b1 ^
b1 M
b1 Q
b1 \
b1 _
b1 N
b1 R
b1 ]
b1 `
b1 I
b1 Y
b1 C
0"
b1 D
1)
b1 '
b1 0
1&
#50000
0&
#55000
b1 B
1"
b10 D
0)
1&
#60000
0&
#65000
b11 D
b1000000000000000 E
b10 B
1&
#70000
0&
#75000
b100 D
b11 B
b1 G
1&
#80000
0&
#85000
b101 D
b1000000000000000 @
b100 B
1&
#90000
0&
#95000
b0 3
b0 J
b0 K
b0 O
b0 1
b0 Z
b0 L
b0 P
b0 [
b0 ^
b0 M
b0 Q
b0 \
b0 _
b0 N
b0 R
b0 ]
b0 `
b110 D
b0 I
b0 Y
b101 B
b100000000000000 E
b0 C
1&
#100000
0&
#105000
b0 D
b110 B
1&
#110000
0&
#115000
b0 B
1#
b1000000000000000 !
b1000000000000000 H
1&
#120000
0&
#125000
0#
b100000000000000 g
b10 h
b1 ,
b1 .
b1 -
1&
#130000
0&
#135000
b10 3
b10 J
b10 K
b10 O
b10 1
b10 Z
b10 L
b10 P
b10 [
b10 ^
b10 M
b10 Q
b10 \
b10 _
b10 N
b10 R
b10 ]
b10 `
b10 I
b10 Y
b10 C
0"
b1 D
1)
b10 '
b10 0
1&
#140000
0&
#145000
1"
b1 B
b10 D
0)
1&
#150000
0&
#155000
b11 D
b10 B
b0 @
b1000000000000000 E
1&
#160000
0&
#165000
b100 D
b0 G
b1 F
b11 B
1&
#170000
0&
#175000
b101 D
b100 B
1&
#180000
0&
#185000
b1 3
b1 J
b1 K
b1 O
b1 1
b1 Z
b1 L
b1 P
b1 [
b1 ^
b1 M
b1 Q
b1 \
b1 _
b1 N
b1 R
b1 ]
b1 `
b1 I
b1 Y
b10 D
b100000000000000 E
b1 C
b101 B
1&
#190000
0&
#195000
b11 D
b10 B
1&
#200000
0&
#205000
b100 D
b1 G
b0 F
b11 B
1&
#210000
0&
#215000
b101 D
b100 B
b100000000000000 @
1&
#220000
0&
#225000
b0 3
b0 J
b0 K
b0 O
b0 1
b0 Z
b0 L
b0 P
b0 [
b0 ^
b0 M
b0 Q
b0 \
b0 _
b0 N
b0 R
b0 ]
b0 `
b0 I
b0 Y
b110 D
b10000000000000 E
b0 C
b101 B
1&
#230000
0&
#235000
b0 D
b110 B
1&
#240000
0&
#245000
1#
b100000000000000 !
b100000000000000 H
b0 B
1&
#250000
0&
#255000
0#
b1100000000000000 g
b11 h
b10 ,
b10 .
b10 -
1&
#260000
0&
#265000
b1 4
b1 T
b11 K
b11 O
b11 1
b11 Z
b11 L
b11 P
b11 [
b11 ^
b11 M
b11 Q
b11 \
b11 _
b11 N
b11 R
b11 ]
b11 `
b11 I
b11 Y
b11 C
0"
b1 D
1)
b11 '
b11 0
1&
#270000
0&
#275000
b1 B
1"
b10 D
0)
1&
#280000
0&
#285000
b11 D
b0 @
b1000000000000000 E
b10 B
1&
#290000
0&
#295000
b100 D
b11 B
b1 F
1&
#300000
0&
#305000
b101 D
b1000000000000000 @
b100 B
1&
#310000
0&
#315000
b0 4
b0 T
b1 3
b1 J
b1 K
b1 O
b1 1
b1 Z
b1 L
b1 P
b1 [
b1 ^
b1 M
b1 Q
b1 \
b1 _
b1 N
b1 R
b1 ]
b1 `
b10 D
b1 I
b1 Y
b101 B
b100000000000000 E
b1 C
1&
#320000
0&
#325000
b11 D
b10 B
1&
#330000
0&
#335000
b100 D
b11 B
b0 F
1&
#340000
0&
#345000
b101 D
b1100000000000000 @
b100 B
1&
#350000
0&
#355000
b0 3
b0 J
b0 K
b0 O
b0 1
b0 Z
b0 L
b0 P
b0 [
b0 ^
b0 M
b0 Q
b0 \
b0 _
b0 N
b0 R
b0 ]
b0 `
b110 D
b0 I
b0 Y
b101 B
b10000000000000 E
b0 C
1&
#360000
0&
#365000
b0 D
b110 B
1&
#370000
0&
#375000
b0 B
1#
b1100000000000000 !
b1100000000000000 H
1&
#380000
0&
#385000
0#
b10000000000000 g
b100 h
b11 ,
b11 .
b11 -
1&
#390000
0&
#395000
b1 3
b1 J
b1 K
b1 O
b100 1
b100 Z
b1 L
b1 P
b100 [
b100 ^
b1 M
b1 Q
b1 4
b1 T
b100 \
b100 _
b1 N
b1 S
b1 X
b100 ]
b100 `
b100 I
b100 Y
b100 C
0"
b1 D
1)
b100 '
b100 0
1&
#400000
0&
#405000
1"
b1 B
b10 D
0)
1&
#410000
0&
#415000
b11 D
b10 B
b0 @
b1000000000000000 E
1&
#420000
0&
#425000
b100 D
b0 G
b10 F
b11 B
1&
#430000
0&
#435000
b101 D
b100 B
1&
#440000
0&
#445000
b10 3
b10 J
b10 K
b10 O
b10 1
b10 Z
b10 L
b10 P
b10 [
b10 ^
b0 4
b0 T
b10 M
b10 Q
b10 \
b10 _
b0 S
b0 X
b10 N
b10 R
b10 ]
b10 `
b10 I
b10 Y
b10 D
b100000000000000 E
b10 C
b101 B
1&
#450000
0&
#455000
b11 D
b10 B
1&
#460000
0&
#465000
b100 D
b1 F
b11 B
1&
#470000
0&
#475000
b101 D
b100 B
1&
#480000
0&
#485000
b1 3
b1 J
b1 K
b1 O
b1 1
b1 Z
b1 L
b1 P
b1 [
b1 ^
b1 M
b1 Q
b1 \
b1 _
b1 N
b1 R
b1 ]
b1 `
b1 I
b1 Y
b10 D
b10000000000000 E
b1 C
b101 B
1&
#490000
0&
#495000
b11 D
b10 B
1&
#500000
0&
#505000
b100 D
b1 G
b0 F
b11 B
1&
#510000
0&
#515000
b101 D
b100 B
b10000000000000 @
1&
#520000
0&
#525000
b0 3
b0 J
b0 K
b0 O
b0 1
b0 Z
b0 L
b0 P
b0 [
b0 ^
b0 M
b0 Q
b0 \
b0 _
b0 N
b0 R
b0 ]
b0 `
b0 I
b0 Y
b110 D
b1000000000000 E
b0 C
b101 B
1&
#530000
0&
#535000
b0 D
b110 B
1&
#540000
0&
#545000
1#
b10000000000000 !
b10000000000000 H
b0 B
1&
#550000
0&
#555000
0#
b1010000000000000 g
b101 h
b100 ,
b100 .
b100 -
1&
#560000
0&
#565000
b10 3
b10 J
b10 K
b10 O
b101 1
b101 Z
b10 L
b10 P
b101 [
b101 ^
b1 4
b1 T
b10 M
b10 Q
b101 \
b101 _
b1 S
b1 X
b10 N
b1 R
b101 ]
b101 `
b101 I
b101 Y
b101 C
0"
b1 D
1)
b101 '
b101 0
1&
#570000
0&
#575000
b1 B
1"
b10 D
0)
1&
#580000
0&
#585000
b11 D
b0 @
b1000000000000000 E
b10 B
1&
#590000
0&
#595000
b100 D
b11 B
b10 F
1&
#600000
0&
#605000
b101 D
b1000000000000000 @
b100 B
1&
#610000
0&
#615000
b10 1
b10 Z
b10 [
b10 ^
b0 4
b0 T
b10 \
b10 _
b0 S
b0 X
b10 N
b10 R
b10 ]
b10 `
b10 D
b10 I
b10 Y
b101 B
b100000000000000 E
b10 C
1&
#620000
0&
#625000
b11 D
b10 B
1&
#630000
0&
#635000
b100 D
b11 B
b0 G
b1 F
1&
#640000
0&
#645000
b101 D
b100 B
1&
#650000
0&
#655000
b1 3
b1 J
b1 K
b1 O
b1 1
b1 Z
b1 L
b1 P
b1 [
b1 ^
b1 M
b1 Q
b1 \
b1 _
b1 N
b1 R
b1 ]
b1 `
b10 D
b1 I
b1 Y
b101 B
b10000000000000 E
b1 C
1&
#660000
0&
#665000
b11 D
b10 B
1&
#670000
0&
#675000
b100 D
b11 B
b1 G
b0 F
1&
#680000
0&
#685000
b101 D
b1010000000000000 @
b100 B
1&
#690000
0&
#695000
b0 3
b0 J
b0 K
b0 O
b0 1
b0 Z
b0 L
b0 P
b0 [
b0 ^
b0 M
b0 Q
b0 \
b0 _
b0 N
b0 R
b0 ]
b0 `
b110 D
b0 I
b0 Y
b101 B
b1000000000000 E
b0 C
1&
#700000
0&
#705000
b0 D
b110 B
1&
#710000
0&
#715000
b0 B
1#
b1010000000000000 !
b1010000000000000 H
1&
#720000
0&
#725000
0#
b1101000000000000 g
b1011 h
b101 ,
b101 .
b101 -
1&
#730000
0&
#735000
b10 3
b10 J
b10 K
b10 O
b100 1
b100 Z
b10 L
b10 P
b100 [
b100 ^
b1 W
b11 4
b11 T
b10 M
b1 Q
b1 2
b1 b
b100 \
b100 _
b11 S
b10 X
b101 N
b11 R
b1 a
b1 e
b100 ]
b11 `
b1011 I
b1011 Y
b1011 C
0"
b1 D
1)
b1011 '
b1011 0
1&
#740000
0&
#745000
1"
b1 B
b10 D
0)
1&
#750000
0&
#755000
b11 D
b10 B
b0 @
b1000000000000000 E
1&
#760000
0&
#765000
b100 D
b101 F
b11 B
1&
#770000
0&
#775000
b101 D
b100 B
b1000000000000000 @
1&
#780000
0&
#785000
b101 1
b101 Z
b101 [
b101 ^
b1 4
b1 T
b0 W
b10 M
b10 Q
b0 2
b0 b
b101 \
b101 _
b1 S
b1 X
b10 N
b1 R
b0 a
b0 e
b101 ]
b101 `
b101 I
b101 Y
b10 D
b100000000000000 E
b101 C
b101 B
1&
#790000
0&
#795000
b11 D
b10 B
1&
#800000
0&
#805000
b100 D
b10 F
b11 B
1&
#810000
0&
#815000
b101 D
b100 B
b1100000000000000 @
1&
#820000
0&
#825000
b10 1
b10 Z
b10 [
b10 ^
b0 4
b0 T
b10 \
b10 _
b0 S
b0 X
b10 N
b10 R
b10 ]
b10 `
b10 I
b10 Y
b10 D
b10000000000000 E
b10 C
b101 B
1&
#830000
0&
#835000
b11 D
b10 B
1&
#840000
0&
#845000
b100 D
b0 G
b1 F
b11 B
1&
#850000
0&
#855000
b101 D
b100 B
1&
#860000
0&
#865000
b1 3
b1 J
b1 K
b1 O
b1 1
b1 Z
b1 L
b1 P
b1 [
b1 ^
b1 M
b1 Q
b1 \
b1 _
b1 N
b1 R
b1 ]
b1 `
b1 I
b1 Y
b10 D
b1000000000000 E
b1 C
b101 B
1&
#870000
0&
#875000
b11 D
b10 B
1&
#880000
0&
#885000
b100 D
b1 G
b0 F
b11 B
1&
#890000
0&
#895000
b101 D
b100 B
b1101000000000000 @
1&
#900000
0&
#905000
b0 3
b0 J
b0 K
b0 O
b0 1
b0 Z
b0 L
b0 P
b0 [
b0 ^
b0 M
b0 Q
b0 \
b0 _
b0 N
b0 R
b0 ]
b0 `
b0 I
b0 Y
b110 D
b100000000000 E
b0 C
b101 B
1&
#910000
0&
#915000
b0 D
b110 B
1&
#920000
0&
#925000
1#
b1101000000000000 !
b1101000000000000 H
b0 B
1&
#930000
0&
#935000
0#
b101010101010101 g
b1 f
b1 h
b0 ,
b110 .
b110 -
1&
#940000
0&
